vcardtools-0.1.1.dist-info/entry_points.txt
vcardtools-0.1.1.dist-info/top_level.txt
vcardtools-0.1.1.dist-info/DESCRIPTION.rst
vcardtools-0.1.1.dist-info/RECORD
vcardtools-0.1.1.dist-info/WHEEL
vcardtools-0.1.1.dist-info/metadata.json
vcardtools-0.1.1.dist-info/METADATA
vcardtools/vcf_splitter.py
vcardtools/vcf_merge.py
vcardtools/__init__.py
vcardtools/vcardtool.py
