Metadata-Version: 2.0
Name: vcardtools
Version: 0.1.1
Summary: Tools to split and merge vCard files.
Home-page: https://github.com/dmwilcox/vcard-tools
Author: Yuba Solutions LLC
Author-email: dmw@yubasoluions.com
License: GPL
Keywords: vCard vcf
Platform: UNKNOWN
Classifier: Development Status :: 3 - Alpha
Classifier: Environment :: Console
Classifier: Intended Audience :: End Users/Desktop
Classifier: License :: OSI Approved :: GNU General Public License (GPL)
Classifier: Operating System :: POSIX
Classifier: Programming Language :: Python :: 2.7
Classifier: Programming Language :: Python :: 3
Classifier: Programming Language :: Python :: 3.4
Classifier: Topic :: Communications :: Email :: Address Book
Classifier: Topic :: Utilities
Requires-Dist: argparse
Requires-Dist: six
Requires-Dist: vobject
